unmarkd/__init__.py
unmarkd/unmarkers.py
unmarkd-1.1.3.dist-info/LICENSE.md
unmarkd-1.1.3.dist-info/METADATA
unmarkd-1.1.3.dist-info/WHEEL
unmarkd-1.1.3.dist-info/RECORD
