Metadata-Version: 2.1
Name: unmarkd
Version: 1.1.3
Summary: A markdown reverser
Home-page: https://github.com/ThatXliner/unmarkd
License: GPL-3.0-or-later
Author: Bryan Hu
Author-email: bryan.hu.2020@gmail.com
Requires-Python: >=3.8,<4.0
Classifier: Development Status :: 5 - Production/Stable
Classifier: License :: OSI Approved :: GNU General Public License v3 or later (GPLv3+)
Classifier: Natural Language :: English
Classifier: Operating System :: OS Independent
Classifier: Programming Language :: Python :: 3
Classifier: Programming Language :: Python :: 3.8
Classifier: Programming Language :: Python :: 3.9
Classifier: Programming Language :: Python :: 3.10
Classifier: Programming Language :: Python :: 3.11
Classifier: Programming Language :: Python :: 3.12
Classifier: Programming Language :: Python :: Implementation :: CPython
Classifier: Topic :: Software Development :: Libraries :: Python Modules
Classifier: Topic :: Text Processing :: Markup :: HTML
Classifier: Topic :: Text Processing :: Markup :: Markdown
Classifier: Typing :: Typed
Requires-Dist: beautifulsoup4 (>=4.12.2)
Project-URL: Documentation, https://unmarkd.readthedocs.io/en/latest/index.html
